[
  {
    "label": "Home",
    "url": "/",
    "children": null
  },
  {
    "label": "Ceremonies",
    "url": "/ceremony",
    "children": [2003, 2005, 2007, 2010, 2012, 2014, 2016, 2018, 2021]
  },
  {
    "label": "Events",
    "url": "/events",
    "children": null
  },
  {
    "label": "Donate",
    "url": "/donate",
    "children": null
  },
  {
    "label": "Contact",
    "url": "/contact",
    "children": null
  },
  {
    "label": "Directory",
    "url": "/directory",
    "children": null
  }
]
